{
  "@microsoft/generator-sharepoint": {
    "plusBeta": false,
    "isCreatingSolution": true,
    "nodeVersion": "16.18.1",
    "sdksVersions": {
      "@microsoft/microsoft-graph-client": "3.0.2",
      "@microsoft/teams-js": "2.4.1"
    },
    "version": "1.16.1",
    "libraryName": "hello-world",
    "libraryId": "37e9f657-457d-435b-8316-053bc0b17d47",
    "environment": "spo",
    "packageManager": "npm",
    "solutionName": "HelloWorld",
    "solutionShortDescription": "HelloWorld description",
    "skipFeatureDeployment": true,
    "isDomainIsolated": false,
    "componentType": "webpart"
  }
}
